fastlmmclib-0.0.7.dist-info/top_level.txt
fastlmmclib-0.0.7.dist-info/RECORD
fastlmmclib-0.0.7.dist-info/LICENSE
fastlmmclib-0.0.7.dist-info/METADATA
fastlmmclib-0.0.7.dist-info/WHEEL
fastlmmclib/quadform/__init__.py
fastlmmclib/quadform/qfc_src/__init__.py
fastlmmclib/quadform/qfc_src/wrap_qfc.cpython-310-aarch64-linux-gnu.so
