Metadata-Version: 2.1
Name: fastlmmclib
Version: 0.0.7
Summary: Fast GWAS C library
Home-page: https://fastlmm.github.io/
Author: FaST-LMM Team
Author-email: fastlmm-dev@python.org
License: Apache 2.0
Project-URL: Bug Tracker, https://github.com/fastlmm/fastlmmclib/issues
Project-URL: Source Code, https://github.com/fastlmm/fastlmmclib
Keywords: gwas bioinformatics LMMs MLMs linear mixed models genomics genetics python
Classifier: Programming Language :: Python :: 3.9
Classifier: Programming Language :: Python :: 3.10
Classifier: Programming Language :: Python :: 3.11
Classifier: Programming Language :: Python :: 3.12
Classifier: Programming Language :: Python :: 3
Classifier: Programming Language :: Python
License-File: LICENSE
Requires-Dist: numpy
